odoo/addons/sale_order_high_priority/README.rst
odoo/addons/sale_order_high_priority/__init__.py
odoo/addons/sale_order_high_priority/__manifest__.py
odoo/addons/sale_order_high_priority/i18n/es.po
odoo/addons/sale_order_high_priority/models/__init__.py
odoo/addons/sale_order_high_priority/models/sale.py
odoo/addons/sale_order_high_priority/static/description/icon.png
odoo14_addon_sale_order_high_priority-14.0.1.0.0.dist-info/METADATA
odoo14_addon_sale_order_high_priority-14.0.1.0.0.dist-info/WHEEL
odoo14_addon_sale_order_high_priority-14.0.1.0.0.dist-info/top_level.txt
odoo14_addon_sale_order_high_priority-14.0.1.0.0.dist-info/RECORD
