Metadata-Version: 2.1
Name: odoo14-addon-sale_order_high_priority
Version: 14.0.1.0.0
Summary: Sale Order Very High Priority
Home-page: https://github.com/OCA/sale-workflow
Author: Sygel, Odoo Community Association (OCA)
Author-email: support@odoo-community.org
License: AGPL-3
Classifier: Programming Language :: Python
Classifier: Framework :: Odoo
Classifier: Framework :: Odoo :: 14.0
Classifier: License :: OSI Approved :: GNU Affero General Public License v3
Requires-Python: >=3.6
Requires-Dist: odoo14-addon-sale-order-priority
Requires-Dist: odoo<14.1dev,>=14.0a
